{
  "mode": "staff",
  "staffName": "担当4",
  "pref": "27",
  "d": "102006001,102006002,102007002,102007003,102007004,102008001,102008002",
  "kinshi": [
    {
      "name": "白銀マンション",
      "addr": "大阪府大阪市都島区都島中通1-4-6",
      "lat": 34.704738148,
      "lng": 135.528286436,
      "staffName": "担当4"
    },
    {
      "name": "メゾンドソレイユ",
      "addr": "大阪府大阪市都島区都島本通4-2",
      "lat": 34.707287,
      "lng": 135.532405,
      "staffName": "担当4"
    },
    {
      "name": "シャトー中島",
      "addr": "大阪府大阪市都島区都島本通4-21-24",
      "lat": 34.707918923,
      "lng": 135.532394475,
      "staffName": "担当4"
    },
    {
      "name": "中島マンションアルタス都島",
      "addr": "大阪府大阪市都島区都島本通4-21-6",
      "lat": 34.708212552,
      "lng": 135.532438894,
      "staffName": "担当4"
    },
    {
      "name": "メゾン・ド・ソレイユ",
      "addr": "大阪府大阪市都島区都島本通4-2-20",
      "lat": 34.705912911000006,
      "lng": 135.532489904,
      "staffName": "担当4"
    },
    {
      "name": "中島マンション別館",
      "addr": "大阪府大阪市都島区都島本通4-23-24",
      "lat": 34.708272496,
      "lng": 135.532462348,
      "staffName": "担当4"
    },
    {
      "name": "シャトー中島別館",
      "addr": "大阪府大阪市都島区都島本通4-23-24",
      "lat": 34.708272496,
      "lng": 135.532462348,
      "staffName": "担当4"
    },
    {
      "name": "プレサンスロジェ都島本通〔イースト・ウエスト〕",
      "addr": "大阪府大阪市都島区都島本通4-8-19",
      "lat": 34.70675748,
      "lng": 135.532002875,
      "staffName": "担当4"
    },
    {
      "name": "古谷（店舗兼住居かも）",
      "addr": "大阪府大阪市都島区都島本通4-1-29",
      "lat": 34.705987268,
      "lng": 135.531013231,
      "staffName": "担当4"
    },
    {
      "name": "古谷様(古谷米穀)",
      "addr": "大阪府大阪市都島区都島本通4-1-29",
      "lat": 34.705987268,
      "lng": 135.531013231,
      "staffName": "担当4"
    },
    {
      "name": "フィオーレ都島北",
      "addr": "大阪府大阪市都島区都島北通1-13-4",
      "lat": 34.710691204,
      "lng": 135.527459201,
      "staffName": "担当4"
    },
    {
      "name": "【3番地全域禁止(ヤ)】",
      "addr": "大阪府大阪市都島区都島北通1-3-6",
      "lat": 34.709356165,
      "lng": 135.528136144,
      "staffName": "担当4"
    },
    {
      "name": "栗原様(栗原ビル)",
      "addr": "大阪府大阪市都島区都島北通1-4-19",
      "lat": 34.709166822,
      "lng": 135.530526473,
      "staffName": "担当4"
    },
    {
      "name": "（戸建）",
      "addr": "大阪府大阪市都島区都島北通2-4-9",
      "lat": 34.709524056,
      "lng": 135.533970466,
      "staffName": "担当4"
    },
    {
      "name": "朝日プラザ都島本通パサージュ",
      "addr": "大阪府大阪市都島区都島北通2-15-12",
      "lat": 34.711041543,
      "lng": 135.531635161,
      "staffName": "担当4"
    },
    {
      "name": "長岡様(戸建)",
      "addr": "大阪府大阪市都島区都島北通2-10-5",
      "lat": 34.710322058,
      "lng": 135.533495449,
      "staffName": "担当4"
    },
    {
      "name": "吉田様(戸建)",
      "addr": "大阪府大阪市都島区都島北通2-5-3",
      "lat": 34.709461105,
      "lng": 135.532285069,
      "staffName": "担当4"
    }
  ]
}