{
  "mode": "staff",
  "staffName": "担当5",
  "pref": "28",
  "d": "202051001,202060002,202064201,202064202,202110002,202118002,202119001,202119002,202119003",
  "kinshi": [
    {
      "name": "タインペリアル南塚口ガーデンハイツ",
      "addr": "名神町2-12-14",
      "lat": 34.7417781,
      "lng": 135.416351,
      "staffName": "担当5"
    },
    {
      "name": "物件不明",
      "addr": "三反田町2丁目11-38",
      "lat": 34.7379032,
      "lng": 135.4078383,
      "staffName": "担当5"
    },
    {
      "name": "刈萩",
      "addr": "三反田町2丁目21-13",
      "lat": 34.7408809,
      "lng": 135.4081245,
      "staffName": "担当5"
    },
    {
      "name": "名称不明",
      "addr": "尼崎市三反田町2-7",
      "lat": 34.7380912,
      "lng": 135.4099509,
      "staffName": "担当5"
    },
    {
      "name": "パレス南塚口1・2号棟",
      "addr": "尾浜町1-32-1・2",
      "lat": 34.7390728,
      "lng": 135.413729,
      "staffName": "担当5"
    },
    {
      "name": "戸建住宅",
      "addr": "尾浜町1-27-19",
      "lat": 34.73819840000001,
      "lng": 135.4139777,
      "staffName": "担当5"
    },
    {
      "name": "南塚口橋本セントラル",
      "addr": "尾浜町1-27-15",
      "lat": 34.7382259,
      "lng": 135.4142723,
      "staffName": "担当5"
    },
    {
      "name": "南塚口橋本セントラル貮番館",
      "addr": "尾浜町1-27-18",
      "lat": 34.7382282,
      "lng": 135.4141204,
      "staffName": "担当5"
    },
    {
      "name": "ホールズ一号館",
      "addr": "尼崎市尾浜町2-7-1",
      "lat": 34.7362692,
      "lng": 135.4158137,
      "staffName": "担当5"
    }
  ]
}